[
	{
		"key": "sb",
		"value": "V7kRYw020mFMC6OWJYQQVmY6",
		"domain": "facebook.com",
		"path": "/",
		"hostOnly": false,
		"creation": "2022-09-25T01:09:34.197Z",
		"lastAccessed": "2022-09-25T01:09:35.909Z"
	},
	{
		"key": "c_user",
		"value": "100068983977008",
		"domain": "facebook.com",
		"path": "/",
		"hostOnly": false,
		"creation": "2022-09-25T01:09:34.312Z",
		"lastAccessed": "2022-09-25T01:09:35.909Z"
	},
	{
		"key": "xs",
		"value": "37%3AROpbYn7PORCX0Q%3A2%3A1663257629%3A-1%3A6235",
		"domain": "facebook.com",
		"path": "/",
		"hostOnly": false,
		"creation": "2022-09-25T01:09:34.369Z",
		"lastAccessed": "2022-09-25T01:09:35.909Z"
	},
	{
		"key": "m_page_voice",
		"value": "100068983977008",
		"domain": "facebook.com",
		"path": "/",
		"hostOnly": false,
		"creation": "2022-09-25T01:09:34.370Z",
		"lastAccessed": "2022-09-25T01:09:35.909Z"
	},
	{
		"key": "fr",
		"value": "0VCAiENR0PqppoDq5.AWVEQBdCpdlz-oJChN0BgMkK6wg.BjEblX.ZX.GMo.0.0.BjKPRq.AWWpabOdYCk",
		"domain": "facebook.com",
		"path": "/",
		"hostOnly": false,
		"creation": "2022-09-25T01:09:34.371Z",
		"lastAccessed": "2022-09-25T01:09:35.909Z"
	},
	{
		"key": "m_pixel_ratio",
		"value": "2.75",
		"domain": "facebook.com",
		"path": "/",
		"hostOnly": false,
		"creation": "2022-09-25T01:09:34.372Z",
		"lastAccessed": "2022-09-25T01:09:35.909Z"
	},
	{
		"key": "x-referer",
		"value": "eyJyIjoiLyIsImgiOiIvIiwicyI6Im0ifQ%3D%3D",
		"domain": "facebook.com",
		"path": "/",
		"hostOnly": false,
		"creation": "2022-09-25T01:09:34.373Z",
		"lastAccessed": "2022-09-25T01:09:35.909Z"
	},
	{
		"key": "wd",
		"value": "393x767",
		"domain": "facebook.com",
		"path": "/",
		"hostOnly": false,
		"creation": "2022-09-25T01:09:34.373Z",
		"lastAccessed": "2022-09-25T01:09:35.909Z"
	},
	{
		"key": "datr",
		"value": "tOcsYzBut06AVk9oJFMokVJe",
		"domain": "facebook.com",
		"path": "/",
		"hostOnly": false,
		"creation": "2022-09-25T01:09:34.374Z",
		"lastAccessed": "2022-09-25T01:09:35.909Z"
	},
	{
		"key": "sb",
		"value": "V7kRYw020mFMC6OWJYQQVmY6",
		"domain": "facebook.com",
		"path": "/",
		"hostOnly": false,
		"creation": "2022-09-25T01:09:34.197Z",
		"lastAccessed": "2022-09-25T01:09:35.909Z"
	},
	{
		"key": "c_user",
		"value": "100068983977008",
		"domain": "facebook.com",
		"path": "/",
		"hostOnly": false,
		"creation": "2022-09-25T01:09:34.312Z",
		"lastAccessed": "2022-09-25T01:09:35.909Z"
	},
	{
		"key": "xs",
		"value": "37%3AROpbYn7PORCX0Q%3A2%3A1663257629%3A-1%3A6235",
		"domain": "facebook.com",
		"path": "/",
		"hostOnly": false,
		"creation": "2022-09-25T01:09:34.369Z",
		"lastAccessed": "2022-09-25T01:09:35.909Z"
	},
	{
		"key": "m_page_voice",
		"value": "100068983977008",
		"domain": "facebook.com",
		"path": "/",
		"hostOnly": false,
		"creation": "2022-09-25T01:09:34.370Z",
		"lastAccessed": "2022-09-25T01:09:35.909Z"
	},
	{
		"key": "fr",
		"value": "0VCAiENR0PqppoDq5.AWVEQBdCpdlz-oJChN0BgMkK6wg.BjEblX.ZX.GMo.0.0.BjKPRq.AWWpabOdYCk",
		"domain": "facebook.com",
		"path": "/",
		"hostOnly": false,
		"creation": "2022-09-25T01:09:34.371Z",
		"lastAccessed": "2022-09-25T01:09:35.909Z"
	},
	{
		"key": "m_pixel_ratio",
		"value": "2.75",
		"domain": "facebook.com",
		"path": "/",
		"hostOnly": false,
		"creation": "2022-09-25T01:09:34.372Z",
		"lastAccessed": "2022-09-25T01:09:35.909Z"
	},
	{
		"key": "x-referer",
		"value": "eyJyIjoiLyIsImgiOiIvIiwicyI6Im0ifQ%3D%3D",
		"domain": "facebook.com",
		"path": "/",
		"hostOnly": false,
		"creation": "2022-09-25T01:09:34.373Z",
		"lastAccessed": "2022-09-25T01:09:35.909Z"
	},
	{
		"key": "wd",
		"value": "393x767",
		"domain": "facebook.com",
		"path": "/",
		"hostOnly": false,
		"creation": "2022-09-25T01:09:34.373Z",
		"lastAccessed": "2022-09-25T01:09:35.909Z"
	},
	{
		"key": "datr",
		"value": "tOcsYzBut06AVk9oJFMokVJe",
		"domain": "facebook.com",
		"path": "/",
		"hostOnly": false,
		"creation": "2022-09-25T01:09:34.374Z",
		"lastAccessed": "2022-09-25T01:09:35.909Z"
	},
	{
		"key": "datr",
		"value": "tOcsYzBut06AVk9oJFMokVJe",
		"domain": "messenger.com",
		"path": "/",
		"hostOnly": false,
		"creation": "2022-09-25T01:09:34.383Z",
		"lastAccessed": "2022-09-25T01:09:35.910Z"
	}
]